Workbook

Sheet June
A1: Item | B1: Budget | C1: Actual | D1: Delta | E1: Notes
A2: Income | B2: -2374.28 | C2: =B2 -> -2374.28 | D2: =IF(ISBLANK(C2),"",B2-C2) -> 0
A3: Standing Charges etc. | B3: 429.55 | C3: =B3 -> 429.55 | D3: =IF(ISBLANK(C3),"",B3-C3) -> 0
A4: Music Lessons | B4: 110 | C4: 110 | D4: =IF(ISBLANK(C4),"",B4-C4) -> 0
A5: Bridge | B5: 50 | C5: 50 | D5: =IF(ISBLANK(C5),"",B5-C5) -> 0
A6: Cash Week 3 June | B6: 30 | C6: 30 | D6: =IF(ISBLANK(C6),"",B6-C6) -> 0
A7: Cash Week 10 June | B7: 30 | C7: 0 | D7: =IF(ISBLANK(C7),"",B7-C7) -> 30
A8: Cash Week 17 June | B8: 30 | C8: 0 | D8: =IF(ISBLANK(C8),"",B8-C8) -> 30
A9: Cash Week 24 June | B9: 30 | C9: 0 | D9: =IF(ISBLANK(C9),"",B9-C9) -> 30
A10: Cash Week 5 | B10: 0 | D10: =IF(ISBLANK(C10),"",B10-C10)
A11: Petrol | B11: 150 | C11: =65.59+68.62 -> 134.21 | D11: =IF(ISBLANK(C11),"",B11-C11) -> 15.79 | E11: Normal + Inverness Trip
A12: Plans | D12: =IF(ISBLANK(C12),"",B12-C12)
D13: =IF(ISBLANK(C13),"",B13-C13)
A14: Amazon Tools | B14: 49 | C14: =B14 -> 49 | D14: =IF(ISBLANK(C14),"",B14-C14) -> 0
A15: Car Insurance | B15: 336 | C15: 336 | D15: =IF(ISBLANK(C15),"",B15-C15) -> 0
A16: Inverness | B16: 150 | C16: =13.56+60+42+19.5+123 -> 258.06 | D16: =IF(ISBLANK(C16),"",B16-C16) -> -108.06 | E16: Wine and snacks from Tesco, cash for bar, boat trip, breakfast, extra night
A17: Genealogy | B17: 75 | C17: 0 | D17: =IF(ISBLANK(C17),"",B17-C17) -> 75
A18: WRHA | B18: 30 | C18: 0 | D18: =IF(ISBLANK(C18),"",B18-C18) -> 30
A19: Amazon Books | B19: 30 | C19: 0.98 | D19: =IF(ISBLANK(C19),"",B19-C19) -> 29.02 | E19: History of EW
A20: Shopping (Mary weekend away) | B20: 50 | C20: =23+5.5+11.59 -> 40.09 | D20: =IF(ISBLANK(C20),"",B20-C20) -> 9.91
A21: Fish for tanks | B21: 50 | C21: =24+9.17 -> 33.17 | D21: =IF(ISBLANK(C21),"",B21-C21) -> 16.83 | E21: 8 Black Mollies + new tank light
A22: Fish for pond | B22: 200 | C22: 0 | D22: =IF(ISBLANK(C22),"",B22-C22) -> 200
A23: Parts for Pond | B23: 300 | C23: =6.61+1.85+27.45+22.04+279.81+11.51+67.97+5.02 -> 422.26 | D23: =IF(ISBLANK(C23),"",B23-C23) -> -122.26 | E23: Screw cups, washers, joins for aluminium tubes, metal for corners + screws and drills, more tubes and fittings+mending plates+more tubes+cable ties
A24: Garden | B24: 100 | C24: =8.38+12 -> 20.38 | D24: =IF(ISBLANK(C24),"",B24-C24) -> 79.62 | E24: Turf, nemaslugs
A25: House | B25: 100 | C25: =24 + 2.94+4.78+10+12.74+5.6+6.95+260+19.82+6.91+31.09+13.99+5.29 -> 404.11 | D25: =IF(ISBLANK(C25),"",B25-C25) -> -304.11 | E25: Paint for ceiling, wooden bead for above door, silver paint, 2 x scotia trims, paint-pots and filler, envelopes, envelopes, new shower, mending plates and WD40, bathroom handle, wallpaper paste and wipes, bathroom wipes,jigsaw blades
A26: Italy v Scotland Rugby Tickets | C26: 266.99 | D26: =IF(ISBLANK(C26),"",B26-C26) -> -266.99
A27: Barcelona Flights | C27: 190 | D27: =IF(ISBLANK(C27),"",B27-C27) -> -190
A28: Mussleburgh Race Tickets | C28: 34 | D28: =IF(ISBLANK(C28),"",B28-C28) -> -34
A29: Carricksoftware.uk domain | C29: 37.5 | D29: =IF(ISBLANK(C29),"",B29-C29) -> -37.5
D32: =SUM(D2:D28) -> -479.25
A33: Balance at end of month | B33: =-SUM(B2:B32) -> 44.73 | C33: =-SUM(C2:C32) -> -472.02 | D33: =B33+D32 -> -434.52
B34: (Plan) | C34: (Current) | D34: (forecast)

Sheet July
A1: Item | B1: Budget | C1: Actual | D1: Delta | E1: Notes
A2: Income | B2: -2923.57 | C2: =B2 -> -2923.57 | D2: =IF(ISBLANK(C2),"",B2-C2) -> 0
A3: Household account | B3: 549.29 | C3: 549.29 | D3: =IF(ISBLANK(C3),"",B3-C3) -> 0
A4: Standing Charges etc. | B4: 433.41 | C4: =B4 -> 433.41 | D4: =IF(ISBLANK(C4),"",B4-C4) -> 0
A5: Music Lessons | B5: 110 | C5: 0 | D5: =IF(ISBLANK(C5),"",B5-C5) -> 110
A6: Bridge | B6: 50 | C6: 50 | D6: =IF(ISBLANK(C6),"",B6-C6) -> 0
A7: Nespresso | B7: 50 | C7: 35 | D7: =IF(ISBLANK(C7),"",B7-C7) -> 15
A8: Amazon books | B8: 30 | C8: =0.98+24.5 -> 25.48 | D8: =IF(ISBLANK(C8),"",B8-C8) -> 4.52 | E8: Scots Guards book 2
A9: Cash Week 1 July | B9: 30 | C9: 0 | D9: =IF(ISBLANK(C9),"",B9-C9) -> 30
A10: Cash Week 8 July | B10: 30 | C10: 0 | D10: =IF(ISBLANK(C10),"",B10-C10) -> 30
A11: Cash Week 15 July | B11: 30 | C11: 0 | D11: =IF(ISBLANK(C11),"",B11-C11) -> 30
A12: Cash Week 22 July | B12: 30 | C12: =4.38+29.96+5.95 -> 40.29 | D12: =IF(ISBLANK(C12),"",B12-C12) -> -10.29 | E12: Coffee while waiting for tribunal, cinema club, cinema
A13: Cash Week 29 July | B13: 30 | C13: =13.96+4.1 -> 18.06 | D13: =IF(ISBLANK(C13),"",B13-C13) -> 11.94 | E13: Paint for airfix models, parking
A14: Petrol | B14: 75 | C14: 73.33 | D14: =IF(ISBLANK(C14),"",B14-C14) -> 1.67
A15: Plans | D15: =IF(ISBLANK(C15),"",B15-C15)
A16: Aviemore Congress Entry | B16: =2*62+2*46 -> 216 | C16: 216 | D16: =IF(ISBLANK(C16),"",B16-C16) -> 0 | E16: Cheque to Bill Richardson
A17: Genealogy | B17: 75 | C17: =30+3.5+14+40 -> 87.5 | D17: =IF(ISBLANK(C17),"",B17-C17) -> -12.5 | E17: Cheque to Sheffield, 15hli war diary, Archie’s medal card, 2 SG war diary, scotlands people
A18: Fish for tanks | B18: 50 | C18: 0 | D18: =IF(ISBLANK(C18),"",B18-C18) -> 50
A19: Parts for Pond | B19: 200 | C19: =13.1+16.44+16.61+146.95+8.2+3.27 -> 204.57 | D19: =IF(ISBLANK(C19),"",B19-C19) -> -4.57 | E19: Netting, post anchors, pipe cement, coastal koi, decking board, screws for frame
A20: Fish and Food for pond | B20: 100 | C20: 32.08 | D20: =IF(ISBLANK(C20),"",B20-C20) -> 67.92 | E20: Stress Coat
A21: Garden | B21: 50 | C21: =12.38+25 -> 37.38 | D21: =IF(ISBLANK(C21),"",B21-C21) -> 12.62 | E21: NemaSlugs, garden collcetion subscription
A22: House | B22: 50 | C22: =99+5+78 -> 182 | D22: =IF(ISBLANK(C22),"",B22-C22) -> -132 | E22: Patio table, play sand, new router
A23: Euros for Barcelona + Euan, Ramsay | B23: 100 | C23: 93.47 | D23: =IF(ISBLANK(C23),"",B23-C23) -> 6.53
A24: Lego | B24: 85 | C24: =84.95+5 -> 89.95 | D24: =IF(ISBLANK(C24),"",B24-C24) -> -4.95 | E24: Lander, spare parts fror DB5
A25: Amy’s flights | B25: 400 | C25: 374 | D25: =IF(ISBLANK(C25),"",B25-C25) -> 26
A26: Musselburgh bets | B26: 70 | C26: 70 | D26: =IF(ISBLANK(C26),"",B26-C26) -> 0
A27: Amy’s birthday | B27: 100 | C27: =13.49+7.49+32 -> 52.98 | D27: =IF(ISBLANK(C27),"",B27-C27) -> 47.02 | E27: Sweets, gin kit, chocolates
A28: Amy’s insurance | B28: 50 | C28: 0 | D28: =IF(ISBLANK(C28),"",B28-C28) -> 50 | E28: Brought forward from August
D29: =IF(ISBLANK(C29),"",B29-C29)
D30: =SUM(D2:D29) -> 328.91
A31: Balance at end of month | B31: =-SUM(B2:B30) -> -70.13 | C31: =-SUM(C2:C30) -> 258.78 | D31: =B31+D30 -> 258.78
B32: (Plan) | C32: (Current) | D32: (forecast)

Sheet August
A1: Item | B1: Budget | C1: Actual | D1: Delta | E1: Notes
A2: Income | B2: =July!B2 -> -2923.57 | C2: =B2 -> -2923.57 | D2: =IF(ISBLANK(C2),"",B2-C2) -> 0
A3: Household Account | B3: 549.29 | C3: 549.29 | D3: =IF(ISBLANK(C3),"",B3-C3) -> 0
A4: Standing Charges etc. | B4: 497.23 | C4: =B4 -> 497.23 | D4: =IF(ISBLANK(C4),"",B4-C4) -> 0
A5: Music Lessons | B5: 110 | C5: 110 | D5: =IF(ISBLANK(C5),"",B5-C5) -> 0
A6: Bridge | B6: 50 | C6: 50 | D6: =IF(ISBLANK(C6),"",B6-C6) -> 0
A7: Nespresso | B7: 50 | C7: 52.3 | D7: =IF(ISBLANK(C7),"",B7-C7) -> -2.3
A8: Amazon books | B8: 30 | C8: 4.99 | D8: =IF(ISBLANK(C8),"",B8-C8) -> 25.01 | E8: Voices of Chernobly for Kindle
A9: Cash Week 5 August | B9: 30 | C9: =4.5+6.5+9.99+17.67+7.25+3.99+4.99+10.75+17.51 -> 83.15 | D9: =IF(ISBLANK(C9),"",B9-C9) -> -53.15 | E9: Lego black 1 x 1 from ebay, Tesco wine, replacement ball pen, humbrol paints X 4 (Amazon), Humbrol
A10: Cash Week 12 August | B10: 30 | C10: =35+23.25 -> 58.25 | D10: =IF(ISBLANK(C10),"",B10-C10) -> -28.25 | E10: Drinks at Hotel du Vin, Nibbles from Morrisons
A11: Cash Week 19 August | B11: 30 | C11: 0 | D11: =IF(ISBLANK(C11),"",B11-C11) -> 30
A12: Cash Week 26 August | B12: 30 | C12: =37.9+7.2+2.7 -> 47.8 | D12: =IF(ISBLANK(C12),"",B12-C12) -> -17.8 | E12: Food from Morrisons, hospital parking, broken lego bricks
A13: Cash Week 5 | B13: 0 | D13: =IF(ISBLANK(C13),"",B13-C13)
A14: Petrol | B14: 75 | C14: 77.85 | D14: =IF(ISBLANK(C14),"",B14-C14) -> -2.85
A15: Plans | D15: =IF(ISBLANK(C15),"",B15-C15)
A16: Genealogy | B16: 75 | C16: =12.95+11+12.95+14+14+120 -> 184.9 | D16: =IF(ISBLANK(C16),"",B16-C16) -> -109.9 | E16: Paternal grandparents wedding certificate, maternal grandparents wedding certificate, Grandfather’s birth certificate, nandad,s death certificate, nanan’s death certificate, find my past
A17: Barcelona | B17: 500 | C17: =8.99+7.07+8.28+1.25+300+40+150+100+38.35 -> 653.94 | D17: =IF(ISBLANK(C17),"",B17-C17) -> -153.94 | E17: Lamp holders, book fro Amy, book for Amy, Frank’s diary notebook, cash on fairfx card, cash for taxi, cash on fairfx, dinner
A18: Tanks | B18: 20 | C18: 11.97 | D18: =IF(ISBLANK(C18),"",B18-C18) -> 8.03 | E18: Holiday block
A19: Pond | B19: 150 | C19: =12.45+22.73+58.79+2.72+2.19 -> 98.88 | D19: =IF(ISBLANK(C19),"",B19-C19) -> 51.12 | E19: UV Lamp, connectors and blue roll, koi food, 40mm stop end, 32mm stop end
A20: Garden | B20: 50 | C20: 49.99 | D20: =IF(ISBLANK(C20),"",B20-C20) -> 0.01 | E20: Strimmer
A21: House | B21: 50 | C21: =6.91+26.99+12.83 -> 46.73 | D21: =IF(ISBLANK(C21),"",B21-C21) -> 3.27 | E21: Window handles for bathroom, powerline extender for down-stairs, rubble bags and padlock for small gate
A22: Lunch/Dinner with Amy | B22: 120 | C22: 171.3 | D22: =IF(ISBLANK(C22),"",B22-C22) -> -51.3 | E22: Yamato was very expensive!
A23: Clothes for USA | B23: 150 | C23: 0 | D23: =IF(ISBLANK(C23),"",B23-C23) -> 150
D24: =IF(ISBLANK(C24),"",B24-C24)
D25: =SUM(D2:D24) -> -152.05
A26: Balance at end of month | B26: =-SUM(B2:B25) -> 327.05 | C26: =-SUM(C2:C25) -> 175 | D26: =B26+D25 -> 175
B27: (Plan) | C27: (Current) | D27: (forecast) | E27: 215

Sheet September
A1: Item | B1: Budget | C1: Actual | D1: Delta | E1: Notes
A2: Income | B2: =July!B2 -> -2923.57 | C2: =B2 -> -2923.57 | D2: =IF(ISBLANK(C2),"",B2-C2) -> 0
A3: Household Account | B3: 549.29 | C3: 549.29 | D3: =IF(ISBLANK(C3),"",B3-C3) -> 0
A4: Standing Charges etc. | B4: 490.64 | C4: =B4 -> 490.64 | D4: =IF(ISBLANK(C4),"",B4-C4) -> 0
A5: Yearly Standing orders | B5: 170 | C5: =40+40+82.34 -> 162.34 | D5: =IF(ISBLANK(C5),"",B5-C5) -> 7.66 | E5: Melville subs(2), VPN
A6: Music Lessons | B6: 110 | C6: 0 | D6: =IF(ISBLANK(C6),"",B6-C6) -> 110
A7: Bridge | B7: 50 | C7: 50 | D7: =IF(ISBLANK(C7),"",B7-C7) -> 0
A8: Nespresso | B8: 55 | C8: 0 | D8: =IF(ISBLANK(C8),"",B8-C8) -> 55
A9: Amazon books | B9: 30 | C9: =0.99+29.24 -> 30.23 | D9: =IF(ISBLANK(C9),"",B9-C9) -> -0.23 | E9: Bumble book, spanish course
A10: Cash Week 2 September | B10: 50 | C10: =7.76+30 -> 37.76 | D10: =IF(ISBLANK(C10),"",B10-C10) -> 12.24 | E10: Paints for shuttle, cash
A11: Cash Week 9 September | B11: 50 | C11: 135 | D11: =IF(ISBLANK(C11),"",B11-C11) -> -85 | E11: Spanish classes for 2.
A12: Cash Week 16 September | B12: 50 | C12: 40.34 | D12: =IF(ISBLANK(C12),"",B12-C12) -> 9.66 | E12: Tom’s Birthday whisky
A13: Cash Week 23 September | B13: 50 | C13: =43.28+18.5 -> 61.78 | D13: =IF(ISBLANK(C13),"",B13-C13) -> -11.78 | E13: Sainsbury’s shopping, razor blades
A14: Cash Week 30 September | B14: 50 | C14: =30+15+4.6 -> 49.6 | D14: =IF(ISBLANK(C14),"",B14-C14) -> 0.4 | E14: Cash, Humble bundle, parking
A15: Petrol | B15: 80 | C15: 69.33 | D15: =IF(ISBLANK(C15),"",B15-C15) -> 10.67
A16: Plans | D16: =IF(ISBLANK(C16),"",B16-C16)
A17: Genealogy | B17: 75 | C17: =11+11+11+11+11+11 -> 66 | D17: =IF(ISBLANK(C17),"",B17-C17) -> 9 | E17: nancy Bramall Birth certificate, her death certificate, Nanan’s birth certificate, Nandad’s birth certificate (possibly), Auntie Violet birth certificate, Aunt Beatrice birth certificate
A18: Tanks | B18: 20 | C18: =17.27+3.39+6.5 -> 27.16 | D18: =IF(ISBLANK(C18),"",B18-C18) -> -7.16 | E18: Perspex for tank tops, scourer, scourer + thermometer
A19: Pond | B19: 150 | C19: =80.85+15.94+9.99 -> 106.78 | D19: =IF(ISBLANK(C19),"",B19-C19) -> 43.22 | E19: Sturgeons, clear water treatment, float switch
A20: Garden | B20: 50 | C20: 49.99 | D20: =IF(ISBLANK(C20),"",B20-C20) -> 0.01 | E20: Fruit Trees (2)
A21: House | B21: 50 | C21: =21.89+27.47+7.98+9+21.99+9.99+18.68 -> 117 | D21: =IF(ISBLANK(C21),"",B21-C21) -> -67 | E21: Paint brushes and mallet for corking wine. wet rot paint and long roller, roller sleeves, paint kettle inserts, REAL white paint, radiator paint, paint and artist brushes
A22: Clothes | B22: 100 | C22: =55.25+49 -> 104.25 | D22: =IF(ISBLANK(C22),"",B22-C22) -> -4.25 | E22: Shoes, trousers
A23: Aviemore Accomodation | B23: 350 | C23: =32+159+100 -> 291 | D23: =IF(ISBLANK(C23),"",B23-C23) -> 59 | E23: Inverness Premier Inn, Aviemore house, Aviemore damage deposit
D25: =SUM(D2:D24) -> 141.44
A26: Balance at end of month | B26: =-SUM(B2:B25) -> 343.64 | C26: =-SUM(C2:C25) -> 485.08 | D26: =B26+D25 -> 485.08
B27: (Plan) | C27: (Current) | D27: (forecast)

Sheet October
A1: Item | B1: Budget | C1: Actual | D1: Delta | E1: Notes
A2: Income | B2: =July!B2 -> -2923.57 | C2: =B2 -> -2923.57 | D2: =IF(ISBLANK(C2),"",B2-C2) -> 0
A3: Household Account | B3: 549.29 | C3: 549.29 | D3: =IF(ISBLANK(C3),"",B3-C3) -> 0
A4: Standing Charges etc. | B4: 489.93 | C4: 492.99 | D4: =IF(ISBLANK(C4),"",B4-C4) -> -3.06
A5: Yearly Standing Order | B5: =48+151 -> 199 | C5: 48.12 | D5: =IF(ISBLANK(C5),"",B5-C5) -> 150.88 | E5: Scot domain name. (Mary paid house insurance)
A6: Music Lessons | B6: 110 | C6: 0 | D6: =IF(ISBLANK(C6),"",B6-C6) -> 110 | E6: One lesson paid in advance from August
A7: Bridge | B7: 50 | C7: 0 | D7: =IF(ISBLANK(C7),"",B7-C7) -> 50
A8: Nespresso | B8: 55 | C8: 53.3 | D8: =IF(ISBLANK(C8),"",B8-C8) -> 1.7
A9: Amazon books | B9: 30 | C9: 9.35 | D9: =IF(ISBLANK(C9),"",B9-C9) -> 20.65 | E9: Spanish activity book
A10: Cash Week 7 October | B10: 50 | C10: =56.5+19+56.88 -> 132.38 | D10: =IF(ISBLANK(C10),"",B10-C10) -> -82.38 | E10: Train to Inverurie, repair to car tyre, Dundee hotel
A11: Cash Week 14 October | B11: 50 | C11: =30+8.8+15.92 -> 54.72 | D11: =IF(ISBLANK(C11),"",B11-C11) -> -4.72 | E11: Cash + Badges for Given + Pizza
A12: Cash Week 21 October | B12: 50 | C12: =7.95+30+15+56.88+3.7 -> 113.53 | D12: =IF(ISBLANK(C12),"",B12-C12) -> -63.53 | E12: Monday Dinner from Asda, cash at Aberdeen, New hedphones for phone, Queens Hotel Dundee, Train Aberdeen to Stonehaven
A13: Cash Week 28 October | B13: 50 | C13: 21 | D13: =IF(ISBLANK(C13),"",B13-C13) -> 29 | E13: Ciinema (3 off)
A14: Cash Week 5 | B14: 0 | D14: =IF(ISBLANK(C14),"",B14-C14)
A15: Petrol | B15: 80 | C15: =44.65+65.87 -> 110.52 | D15: =IF(ISBLANK(C15),"",B15-C15) -> -30.52
A16: Plans | D16: =IF(ISBLANK(C16),"",B16-C16)
A17: Genealogy | B17: 75 | C17: =4.99+20+10.95+10.95+20+12.95 -> 79.84 | D17: =IF(ISBLANK(C17),"",B17-C17) -> -4.84 | E17: Parking to take in REME, 80 credits from Scotland’s peopl, Annei Grant and Andrew Grant marriage certificate, great gandad’s bith certificate, 80 credits from Scotlands’ People, Annie Grant death certificate
A18: Tanks | B18: 30 | C18: 31 | D18: =IF(ISBLANK(C18),"",B18-C18) -> -1 | E18: Three cichlids and some food for them
A19: Pond | B19: 150 | C19: =19.97 -> 19.97 | D19: =IF(ISBLANK(C19),"",B19-C19) -> 130.03 | E19: Stress Coat
A20: Garden | B20: 50 | C20: 0 | D20: =IF(ISBLANK(C20),"",B20-C20) -> 50
A21: House | B21: 50 | C21: =16.24+17.84 -> 34.08 | D21: =IF(ISBLANK(C21),"",B21-C21) -> 15.92 | E21: Replacement plunge saw blades, ceramic poppies for all
A22: Sheffield visit | B22: 300 | C22: =54.59+80+56+47+30+12+15+9+9.17 -> 312.76 | D22: =IF(ISBLANK(C22),"",B22-C22) -> -12.76 | E22: Sheffield Hotel, Crucible theatre, Scraborough theatre, Scarboarogh dinner, cash, cocktails etc., parking, coffess
A23: Clothes | B23: 100 | C23: =54.5+85 -> 139.5 | D23: =IF(ISBLANK(C23),"",B23-C23) -> -39.5 | E23: M & S jersey and belt, Blacks – walking shoes
A24: Glasses | B24: 250 | C24: =30+272 -> 302 | D24: =IF(ISBLANK(C24),"",B24-C24) -> -52 | E24: Parking fine in Dalkeith, glasses
D26: =SUM(D2:D24) -> 263.87
A27: Balance at end of month | B27: =-SUM(B2:B24) -> 155.35 | C27: =-SUM(C2:C24) -> 419.22 | D27: =B27+D26 -> 419.22
B28: (Plan) | C28: (Current) | D28: (forecast)

Sheet November
A1: Item | B1: Budget | C1: Actual | D1: Delta | E1: Notes
A2: Income | B2: =July!B2 -> -2923.57 | C2: =B2 -> -2923.57 | D2: =IF(ISBLANK(C2),"",B2-C2) -> 0
A3: Household Account | B3: 549.29 | C3: 549.29 | D3: =IF(ISBLANK(C3),"",B3-C3) -> 0
A4: Standing Charges etc. | B4: 564.99 | C4: =B4 -> 564.99 | D4: =IF(ISBLANK(C4),"",B4-C4) -> 0
A5: Yearly Standing Order | B5: 199 | C5: 238.8 | D5: =IF(ISBLANK(C5),"",B5-C5) -> -39.8 | E5: Forgot VAT!
A6: Music Lessons | B6: 110 | C6: 0 | D6: =IF(ISBLANK(C6),"",B6-C6) -> 110 | E6: One lesson paid in advance from August
A7: Bridge | B7: 75 | C7: =50+5.5 -> 55.5 | D7: =IF(ISBLANK(C7),"",B7-C7) -> 19.5 | E7: Credits and Barley Sugar
A8: Nespresso | B8: 55 | C8: 0 | D8: =IF(ISBLANK(C8),"",B8-C8) -> 55
A9: Amazon books | B9: 30 | C9: 0 | D9: =IF(ISBLANK(C9),"",B9-C9) -> 30
A10: Cash Week 4 November | B10: 50 | C10: 50 | D10: =IF(ISBLANK(C10),"",B10-C10) -> 0
A11: Cash Week 11 November | B11: 50 | C11: =1.8+6.8 -> 8.6 | D11: =IF(ISBLANK(C11),"",B11-C11) -> 41.4 | E11: Newspaper, cinema
A12: Cash Week 18 November | B12: 50 | C12: =39.8+100+50 -> 189.8 | D12: =IF(ISBLANK(C12),"",B12-C12) -> -139.8 | E12: Dinner at Cool Jade, top ub HSBC, cash for antiques fair
A13: Cash Week 25 November | B13: 50 | C13: =3.3+2.1 -> 5.4 | D13: =IF(ISBLANK(C13),"",B13-C13) -> 44.6 | E13: Monday breakfast, monday lunch
A14: Cash Week 5 | B14: 0 | D14: =IF(ISBLANK(C14),"",B14-C14)
A15: Petrol | B15: 80 | C15: =63.37+11.99+68.15 -> 143.51 | D15: =IF(ISBLANK(C15),"",B15-C15) -> -63.51 | E15: Fuel at perth+Adblu (Amazon)
A16: Plans | D16: =IF(ISBLANK(C16),"",B16-C16)
A17: Genealogy | B17: 75 | C17: =14.15+20+14.15+14.15 -> 62.45 | D17: =IF(ISBLANK(C17),"",B17-C17) -> 12.55 | E17: GGF and annie re-order, scolands people credits, granny’s birth certificate, grany’s mother birth certificate
A18: Tanks | B18: 30 | C18: 20 | D18: =IF(ISBLANK(C18),"",B18-C18) -> 10 | E18: Three yellow chichlids
A19: Pond | B19: 100 | C19: 0 | D19: =IF(ISBLANK(C19),"",B19-C19) -> 100
A20: Garden | B20: 50 | C20: 0 | D20: =IF(ISBLANK(C20),"",B20-C20) -> 50
A21: House | B21: 50 | C21: =1.5+6.99 -> 8.49 | D21: =IF(ISBLANK(C21),"",B21-C21) -> 41.51 | E21: Oxo cubes, mouse traps
A22: Xmas presents part 1 | B22: 300 | C22: =76+13.7+8+8.66+35.3+64.98+134+14+4.2+18.67+12.05 -> 389.56 | D22: =IF(ISBLANK(C22),"",B22-C22) -> -89.56 | E22: David’s birthday (Colonades) + Cards and calendar from HFH + advent calendars + cat calendars + Abi cricket top+Dvaid Cricket top+EBU Entry, Books for Ryland (2nd try), envelope for Amy’s parcel, pos Amy’s parcel, Ryland’s advent calendar
A23: Mary’s Birthday extras | B23: 100 | C23: =2*67+116.3 -> 250.3 | D23: =IF(ISBLANK(C23),"",B23-C23) -> -150.3 | E23: Blackpool congress + travel from Gl;asgow
A24: Inverness/Aviemore trip | B24: 200 | C24: =49 +5.6+49+40+5.46+0.45+14.69+2.2+54.35 -> 220.75 | D24: =IF(ISBLANK(C24),"",B24-C24) -> -20.75 | E24: ?, ? , Dinner, cash, flowers, snacks, lunch, parking, dinner
A25: Clothes | B25: 50 | C25: =37.6 -> 37.6 | D25: =IF(ISBLANK(C25),"",B25-C25) -> 12.4 | E25: socks, pants, gloves
D27: =SUM(D2:D25) -> 23.24
A28: Balance at end of month | B28: =-SUM(B2:B25) -> 105.29 | C28: =-SUM(C2:C23) -> 386.88 | D28: =B28+D27 -> 128.53
B29: (Plan) | C29: (Current) | D29: (forecast)

Sheet December
A1: Item | B1: Budget | C1: Actual | D1: Delta | E1: Notes
A2: Income | B2: =July!B2 -> -2923.57 | C2: =B2 -> -2923.57 | D2: =IF(ISBLANK(C2),"",B2-C2) -> 0
A3: Household Account | B3: 549.29 | C3: 549.29 | D3: =IF(ISBLANK(C3),"",B3-C3) -> 0
A4: Standing Charges etc. | B4: 564.99 | C4: =B4 -> 564.99 | D4: =IF(ISBLANK(C4),"",B4-C4) -> 0
A5: Yearly Standing Order | B5: 0 | D5: =IF(ISBLANK(C5),"",B5-C5)
A6: Music Lessons | B6: 110 | C6: 0 | D6: =IF(ISBLANK(C6),"",B6-C6) -> 110 | E6: One lesson paid in advance from August
A7: Bridge | B7: 75 | C7: 75 | D7: =IF(ISBLANK(C7),"",B7-C7) -> 0 | E7: Melville top up (inc party)
A8: Nespresso | B8: 55 | C8: 0 | D8: =IF(ISBLANK(C8),"",B8-C8) -> 55
A9: Amazon books | B9: 30 | C9: 0 | D9: =IF(ISBLANK(C9),"",B9-C9) -> 30
A10: Cash Week 2 December | B10: 50 | C10: =7.99 -> 7.99 | D10: =IF(ISBLANK(C10),"",B10-C10) -> 42.01 | E10: Hand warmers
A11: Cash Week 9 December | B11: 50 | C11: =20+6.75+80+ 2.49+10 -> 119.24 | D11: =IF(ISBLANK(C11),"",B11-C11) -> -69.24 | E11: Cash + papers + Mary’s next birthday dinner, kitchen aerator+test of Marcus link
A12: Cash Week 16 December | B12: 50 | C12: 0 | D12: =IF(ISBLANK(C12),"",B12-C12) -> 50
A13: Cash Week 23 December | B13: 50 | C13: =40+3.5+21 -> 64.5 | D13: =IF(ISBLANK(C13),"",B13-C13) -> -14.5 | E13: cash + Parking Broughton Street+Amy breakfast
A14: Cash Week 30 December | B14: 50 | C14: =4.3+29.06+6.5 -> 39.86 | D14: =IF(ISBLANK(C14),"",B14-C14) -> 10.14 | E14: Parking for brunch with Gillian, Cinema, fame for Ryland’s picture
A15: Petrol | B15: 80 | C15: 63.37 | D15: =IF(ISBLANK(C15),"",B15-C15) -> 16.63
A16: Plans | D16: =IF(ISBLANK(C16),"",B16-C16)
A17: Genealogy | B17: 75 | C17: =30+20+34.15+20 -> 104.15 | D17: =IF(ISBLANK(C17),"",B17-C17) -> -29.15 | E17: Tickets for search room, credits, Robert Mclennan marriage cert, credits
A18: Tanks | B18: 30 | C18: 0 | D18: =IF(ISBLANK(C18),"",B18-C18) -> 30
A19: Pond | B19: 50 | C19: 0 | D19: =IF(ISBLANK(C19),"",B19-C19) -> 50
A20: Garden | B20: 50 | C20: 0 | D20: =IF(ISBLANK(C20),"",B20-C20) -> 50
A21: House | B21: 50 | C21: =17.99+15.85+6.99 -> 40.83 | D21: =IF(ISBLANK(C21),"",B21-C21) -> 9.17 | E21: Pack of 6 ES lamps, PP3 batteries and brandy snaps, capsule lamps
A22: Xmas presents part 2 and costs | B22: 400 | C22: =345+17.4+251.23+34.66+17.12+22.14+18.99+25.99+36+61+35+9.99+63.99+11.99+7.49 -> 957.99 | D22: =IF(ISBLANK(C22),"",B22-C22) -> -557.99 | E22: Lego excavator, Mary’s cake and card, Amy’s TV, Ryland’s train, juggling balls, cat calendar, James shirt, james shirt, books, new brooch for Liz, extra juggling balls and books + scissors, mary’s mouse, extra scisors and shears
A23: Blackpool or similar | B23: 200 | C23: =40+2+55.8+42+8.7+8.7+11.3+38+5.15 -> 211.65 | D23: =IF(ISBLANK(C23),"",B23-C23) -> -11.65 | E23: Cash, coach booking, Steak in Wotherspoons, chinese meal, two tickets from Quens Street, cofeee wirth the family, hotrl drinks, hotel drinks, cofee in town
A24: James in Edinburgh | B24: 150 | C24: =10+13+20+20+76+20+241+2.5 -> 402.5 | D24: =IF(ISBLANK(C24),"",B24-C24) -> -252.5 | E24: Tiger who came to tea book and toy, airport parking (x2), airport parkign again, Cool Jade3, Amy Parking
A25: Works outings | B25: 100 | C25: =50+50 -> 100 | D25: =IF(ISBLANK(C25),"",B25-C25) -> 0 | E25: Cash for Selex, and phartes
A26: Clothes | B26: 100 | C26: 0 | D26: =IF(ISBLANK(C26),"",B26-C26) -> 100
D28: =SUM(D2:D26) -> -382.08
A29: Balance at end of month | B29: =-SUM(B2:B26) -> 4.29 | C29: =-SUM(C2:C26) -> -377.79 | D29: =B29+D28 -> -377.79
B30: (Plan) | C30: (Current) | D30: (forecast)
A34: Cash at Start of Month (1/12/2019) | B34: 3094.87
A35: Less pension payments (except Aviva) | B35: =2923.56-801.52 -> 2122.04
A36: Net (? Free cash) | B36: =B34-B35 -> 972.83
